MANIFEST.in
README.rst
setup.py
collective/__init__.py
collective.jqhistory.egg-info/PKG-INFO
collective.jqhistory.egg-info/SOURCES.txt
collective.jqhistory.egg-info/dependency_links.txt
collective.jqhistory.egg-info/entry_points.txt
collective.jqhistory.egg-info/namespace_packages.txt
collective.jqhistory.egg-info/not-zip-safe
collective.jqhistory.egg-info/requires.txt
collective.jqhistory.egg-info/top_level.txt
collective/jqhistory/__init__.py
collective/jqhistory/configure.zcml
collective/jqhistory/jquery.history.js
collective/jqhistory/profiles/default/jsregistry.xml
collective/jqhistory/profiles/default/metadata.xml
docs/HISTORY.txt
docs/LICENSE.txt
docs/agpl-3.0.txt
docs/jquery-history-COPYING.txt