Metadata-Version: 1.0
Name: collective.jqhistory
Version: 1.0.1
Summary: Packages up the jquery-history plugin for plone.
Home-page: https://github.com/collective/collective.jqhistory/
Author: 4teamwork GmbH
Author-email: mailto:info@4teamwork.ch
License: AGPL3
Keywords: jquery history collective plone
Platform: UNKNOWN
Classifier: Framework :: Plone
Classifier: Framework :: Plone :: 4.0
Classifier: Framework :: Plone :: 4.1
Classifier: License :: OSI Approved :: GNU Affero General Public License v3Programming Language :: Python
Classifier: Topic :: Software Development :: Libraries :: Python Modules
